LICENSE
MANIFEST.in
README
README.md
setup.py
acthex/__init__.py
acthex/actionmanager.py
acthex/main.py
acthex/rewriter.py
dlvhex/__init__.py
hexlite/__init__.py
hexlite/app.py
hexlite/auxiliary.py
hexlite/buildclingo.py
hexlite/clingobackend.py
hexlite/clingogroundprogramprinter.py
hexlite/common.py
hexlite/explicitflpcheck.py
hexlite/main.py
hexlite/modelcallback.py
hexlite/rewriter.py
hexlite.egg-info/PKG-INFO
hexlite.egg-info/SOURCES.txt
hexlite.egg-info/dependency_links.txt
hexlite.egg-info/entry_points.txt
hexlite.egg-info/not-zip-safe
hexlite.egg-info/requires.txt
hexlite.egg-info/top_level.txt
hexlite/ast/__init__.py
hexlite/ast/shallowparser.py